{
	"modulos": [
		{
			"nombre": "M-01 – Atención al Cliente",
			"modulosPrincipales": [
				{
					"nombre": "Portal Transaccional",
					"submodulos": [
						{
							"nombre": "Mi perfil de usuario",
							"funcionalidades": [
								{
									"nombre": "Registro de usuarios",
									"tareas": [
										{"nombre": "Creación de usuarios"},
										{"nombre": "Validación de datos de identidad"}
									],
								},
								{
									"nombre": "Seguridad",
									"tareas": [
										{"nombre": "Gestión de contraseña"},
										{"nombre": "Gestionar token de seguridad  - firma"}
									],
								},
								{
									"nombre": "Configuración",
									"tareas": [
										{"nombre": "Preferencias - Foto de perfil"},
										{"nombre": "Personalización de experiencia de usuario de acuerdo al protocolo de relacionamiento con el ciudadano y la información de registro"}
									]
								}
							],
						},
						{
							"nombre": "Trámites y Servicios TACI",
							"funcionalidades": [
								{
									"nombre": "Frame de acceso a trámites",
									"tareas": [
										{"nombre": "Listar trámites"}
									]
								}
							]
						}
					]
				}
			]
		}
	]
}